{
  "parent": "minecraft:recipes/root",
  "rewards": {
    "recipes": [
      "cosmere:metalworking_table"
    ]
  },
  "criteria": {
    "has_material": {
      "trigger": "minecraft:inventory_changed",
      "conditions": {
        "items": [
          {
            "tag": "forge:ingots"
          }
        ]
      }
    },
    "has_the_recipe": {
      "trigger": "minecraft:recipe_unlocked",
      "conditions": {
        "recipe": "cosmere:metalworking_table"
      }
    }
  },
  "requirements": [
    [
      "has_material",
      "has_the_recipe"
    ]
  ]
}